RT_OOE/__init__.py
rt_ooe-0.0.1.dist-info/licenses/LICENSE
rt_ooe-0.0.1.dist-info/METADATA
rt_ooe-0.0.1.dist-info/WHEEL
rt_ooe-0.0.1.dist-info/top_level.txt
rt_ooe-0.0.1.dist-info/RECORD
